ChangeLog
LICENSE
MANIFEST.in
README.md
setup.py
doc/wiki.md
kindlepush/__init__.py
kindlepush/kindle.py
kindlepush.egg-info/PKG-INFO
kindlepush.egg-info/SOURCES.txt
kindlepush.egg-info/dependency_links.txt
kindlepush.egg-info/entry_points.txt
kindlepush.egg-info/requires.txt
kindlepush.egg-info/top_level.txt