Metadata-Version: 1.1
Name: kindlepush
Version: 0.3.2
Summary: Automatically send your doc to your kindle without clicking the deliver button for 3G device
Home-page: https://github.com/lord63/kindledxpush
Author: lord63
Author-email: lord63.j@gmail.com
License: MIT
Keywords: kindle push automatically 3G
Platform: UNKNOWN
Classifier: Development Status :: 4 - Beta
Classifier: Operating System :: POSIX
Classifier: Operating System :: POSIX :: Linux
Classifier: License :: OSI Approved :: MIT License
Classifier: Programming Language :: Python :: 2
Classifier: Programming Language :: Python :: 2.6
Classifier: Programming Language :: Python :: 2.7
